{
  "authInfo": {
    "2H3JSRBZ2": {
      "readers": [],
      "owners": [],
      "writers": [],
      "runners": []
    },
    "2H4369XDE": {
      "readers": [],
      "owners": [],
      "writers": [],
      "runners": []
    },
    "2H49HPNTM": {
      "readers": [],
      "owners": [],
      "writers": [],
      "runners": []
    },
    "2GWV7EGTC": {
      "readers": [],
      "owners": [],
      "writers": [],
      "runners": []
    },
    "2H5WXKFUX": {
      "readers": [],
      "owners": [],
      "writers": [],
      "runners": []
    },
    "2H3NNS7KY": {
      "readers": [],
      "owners": [],
      "writers": [],
      "runners": []
    },
    "2H4GUNJ5R": {
      "readers": [],
      "owners": [],
      "writers": [],
      "runners": []
    },
    "2FR8ZGGEJ": {
      "readers": [],
      "owners": [],
      "writers": [],
      "runners": []
    },
    "2H52G3TVJ": {
      "readers": [],
      "owners": [],
      "writers": [],
      "runners": []
    },
    "2GJG86W7M": {
      "readers": [],
      "owners": [],
      "writers": [],
      "runners": []
    },
    "2GXP5YHTA": {
      "readers": [],
      "owners": [],
      "writers": [],
      "runners": []
    },
    "2H3BCUTWM": {
      "readers": [],
      "owners": [],
      "writers": [],
      "runners": []
    }
  }
}